hello.py
helloxyz-0.0.2.dist-info/METADATA
helloxyz-0.0.2.dist-info/WHEEL
helloxyz-0.0.2.dist-info/license.txt
helloxyz-0.0.2.dist-info/top_level.txt
helloxyz-0.0.2.dist-info/RECORD
