Metadata-Version: 2.1
Name: helloxyz
Version: 0.0.2
Summary: Say hello!
Home-page: UNKNOWN
Author: Ashwin Bala
Author-email: ashwinbala1999@gmail.com
License: UNKNOWN
Platform: UNKNOWN
Classifier: Programming Language :: Python :: 3.0
Classifier: Programming Language :: Python :: 3.8
Classifier: Programming Language :: Python :: 3.9
Classifier: Operating System :: OS Independent
Classifier: License :: OSI Approved :: MIT License
